corpusinterface/__init__.py
corpusinterface/config.py
corpusinterface/corpora.py
corpusinterface/default_config.ini
corpusinterface/loading.py
corpusinterface/util.py
corpusinterface-0.1.5.dist-info/METADATA
corpusinterface-0.1.5.dist-info/WHEEL
corpusinterface-0.1.5.dist-info/top_level.txt
corpusinterface-0.1.5.dist-info/RECORD
