Metadata-Version: 2.1
Name: corpusinterface
Version: 0.1.5
Summary: tools for loading corpora
Home-page: https://github.com/DCMLab/corpusinterface
Author: Robert Lieck
Author-email: robert.lieck@epfl.ch
Classifier: Programming Language :: Python :: 3
Classifier: License :: OSI Approved :: GNU General Public License v3 (GPLv3)
Classifier: Operating System :: OS Independent
Requires-Python: >=3.8
Requires-Dist: GitPython
Requires-Dist: pandas
